odoo/addons/remove_button_access/__manifest__.py
odoo/addons/remove_button_access/data/mail_data.xml
odoo14_addon_remove_button_access-14.0.1.0.1.dist-info/METADATA
odoo14_addon_remove_button_access-14.0.1.0.1.dist-info/WHEEL
odoo14_addon_remove_button_access-14.0.1.0.1.dist-info/top_level.txt
odoo14_addon_remove_button_access-14.0.1.0.1.dist-info/RECORD
