Metadata-Version: 2.1
Name: odoo14-addon-remove-button-access
Version: 14.0.1.0.1
Summary: Remove the button "View ..." from chatter email templates
Home-page: https://coopdevs.org
Author: Coopdevs Treball SCCL
License: AGPL-3
Platform: UNKNOWN
Classifier: Programming Language :: Python
Classifier: Framework :: Odoo
Classifier: License :: OSI Approved :: GNU Affero General Public License v3
Requires-Python: >=3.6
Requires-Dist: odoo (<14.1dev,>=14.0a)
